timekit/__init__.py
timekit/client.py
timekit/components/__init__.py
timekit/components/apps.py
timekit/components/availability.py
timekit/components/base.py
timekit/components/bookings.py
timekit/components/projects.py
timekit/components/resources.py
python_timekit-1.0.2.dist-info/LICENSE.txt
python_timekit-1.0.2.dist-info/METADATA
python_timekit-1.0.2.dist-info/WHEEL
python_timekit-1.0.2.dist-info/top_level.txt
python_timekit-1.0.2.dist-info/RECORD
