Metadata-Version: 2.1
Name: python-timekit
Version: 1.0.2
Summary: An un-official package to integrate Timekit APIs with your project
Home-page: https://github.com/Srijan-Ramavat/python-timekit
Author: Srijan Ramavat
Author-email: srijan.ramavat@gmail.com
Classifier: Programming Language :: Python :: 3
Classifier: Programming Language :: Python :: 3.6
Classifier: Programming Language :: Python :: 3.7
Classifier: Programming Language :: Python :: 3.8
Classifier: Programming Language :: Python :: 3.9
Classifier: License :: OSI Approved :: GNU General Public License v3 or later (GPLv3+)
Classifier: Operating System :: OS Independent
Classifier: Development Status :: 5 - Production/Stable
Classifier: Topic :: Internet
Classifier: Topic :: Office/Business
Classifier: Topic :: Software Development :: Libraries :: Python Modules
License-File: LICENSE.txt
Requires-Dist: requests (==2.28.1)
